{"assets":{"D88296A57128D65D7F60CFEBFF9D4F04":{"type":"texture","index":3,"assetRequest":{"type":"slide","state":"contents","slide":"none"},"url":{"native":"assets\/75B3C825-57FB-457B-9333-707D6ED54BFD.pdf"},"width":153,"height":144},"4CF0339B3675E8219B2D03F2AEDA6480":{"type":"texture","index":2,"assetRequest":{"type":"slide","state":"contents","slide":"none"},"url":{"native":"assets\/75B3C825-57FB-457B-9333-707D6ED54BFD.pdf"},"width":152,"height":77},"6C75AA76F78CD896B5939358DD4B7400":{"type":"texture","index":4,"assetRequest":{"type":"slide","state":"contents","slide":"none"},"url":{"native":"assets\/75B3C825-57FB-457B-9333-707D6ED54BFD.pdf"},"width":970,"height":643},"20B48E0268FDEF10A2E2CC5243133BCA":{"type":"texture","index":6,"assetRequest":{"type":"slide","state":"contents","slide":"none"},"url":{"native":"assets\/75B3C825-57FB-457B-9333-707D6ED54BFD.pdf"},"width":720,"height":540},"061E52036B4D717608B06786659BDA42":{"type":"texture","index":0,"assetRequest":{"type":"slide","state":"contents","slide":"none"},"url":{"native":"assets\/75B3C825-57FB-457B-9333-707D6ED54BFD.pdf"},"width":720,"height":540},"4DE4776D86FE7C2E8679BF85BF26A28C":{"type":"texture","index":1,"assetRequest":{"type":"slide","state":"contents","slide":"none"},"url":{"native":"assets\/75B3C825-57FB-457B-9333-707D6ED54BFD.pdf"},"width":311,"height":215},"EE4ED503C1F8A585FBFC66F1850A8D58":{"type":"texture","index":5,"assetRequest":{"type":"slide","state":"contents","slide":"none"},"url":{"native":"assets\/75B3C825-57FB-457B-9333-707D6ED54BFD.pdf"},"width":720,"height":540}},"events":[{"effects":[{"beginTime":0,"baseLayer":{"animations":[],"initialState":{"affineTransform":[1,0,0,1,0,0],"masksToBounds":false,"rotation":0,"scale":1,"position":{"pointX":344.54765319824219,"pointY":300.96777153015137},"width":970,"sublayerTransform":[1,0,0,0,0,1,0,0,0,0,1,0,0,0,0,1],"contentsRect":{"y":0,"x":0,"width":1,"height":1},"opacity":1,"edgeAntialiasingMask":251658240,"height":643,"hidden":false,"anchorPoint":{"pointX":0.5,"pointY":0.5}},"objectID":"C773AFBD-4669-4E31-84E7-6E9044E3878D","layers":[{"animations":[],"initialState":{"affineTransform":[1,0,0,1,0,0],"masksToBounds":false,"rotation":0,"scale":1,"position":{"pointX":500.45234680175781,"pointY":290.53222846984863},"width":970,"sublayerTransform":[1,0,0,0,0,1,0,0,0,0,1,-0.00070015824933551967,0,0,0,1],"contentsRect":{"y":0,"x":0,"width":1,"height":1},"opacity":1,"edgeAntialiasingMask":251658240,"height":643,"hidden":false,"anchorPoint":{"pointX":0.51593025443480189,"pointY":0.4518386134834349}},"layers":[{"animations":[{"timeOffset":0,"beginTime":1e-100,"repeatCount":0,"animations":[{"timeOffset":0,"from":{"scalar":0},"beginTime":0,"repeatCount":0,"fillMode":"both","duration":2.5,"autoreverses":false,"timingFunction":"EaseInEaseOut","property":"opacity","to":{"scalar":1}},{"timeOffset":0,"from":{"scalar":false},"beginTime":0,"repeatCount":0,"fillMode":"forwards","property":"hidden","autoreverses":false,"duration":2.5,"to":{"scalar":false}}],"fillMode":"both","autoreverses":false,"duration":2.5}],"layers":[],"texturedRectangle":{"isBackgroundTexture":true,"singleTextureOpacity":1,"textureType":5,"textBaseline":0,"textXHeight":0,"isVerticalText":false},"initialState":{"affineTransform":[1,0,0,1,0,0],"masksToBounds":false,"rotation":0,"scale":1,"position":{"pointX":483.45234680175781,"pointY":320.03222846984863},"width":970,"sublayerTransform":[1,0,0,0,0,1,0,0,0,0,1,0,0,0,0,1],"contentsRect":{"y":0,"x":0,"width":1,"height":1},"opacity":1,"edgeAntialiasingMask":0,"height":643,"hidden":true,"anchorPoint":{"pointX":0.5,"pointY":0.5}},"texture":"6C75AA76F78CD896B5939358DD4B7400"}]}]},"effects":[],"duration":2.5,"type":"buildIn","attributes":{"KNBuildCustomAttributesShine":true,"direction":0,"KNBuildCustomAttributesScaleAmount":70},"name":"com.apple.iWork.Keynote.FromDarkness","objectID":"C773AFBD-4669-4E31-84E7-6E9044E3878D"}],"automaticPlay":false,"hyperlinks":[],"accessibility":[{"text":"Pages from Logo_presentation.pdf","targetRectangle":{"y":397.11660766601562,"x":575.41827392578125,"width":150,"height":140.99588012695312}},{"text":"rhulmasterlogocmyk.jpg","targetRectangle":{"y":20,"x":544,"width":150,"height":74.920677185058594}},{"text":"A quick word!","targetRectangle":{"y":150.70000457763672,"x":128.2547766852191,"width":307.81250917352736,"height":91}},{"text":" \\tHugh Shanahan ","targetRectangle":{"y":288.30000615119934,"x":128.2547766852191,"width":227.39063046667741,"height":60.000000655651093}},{"text":" \\tDirector of Student Experience","targetRectangle":{"y":348.30000680685043,"x":128.2547766852191,"width":293.66667410852403,"height":41}}],"baseLayer":{"animations":[],"initialState":{"affineTransform":[1,0,0,1,0,0],"masksToBounds":false,"rotation":0,"scale":1,"position":{"pointX":360,"pointY":270},"width":720,"sublayerTransform":[1,0,0,0,0,1,0,0,0,0,1,0,0,0,0,1],"contentsRect":{"y":0,"x":0,"width":1,"height":1},"opacity":1,"edgeAntialiasingMask":251658240,"height":540,"hidden":false,"anchorPoint":{"pointX":0.5,"pointY":0.5}},"layers":[{"animations":[],"initialState":{"affineTransform":[1,0,0,1,0,0],"masksToBounds":false,"rotation":0,"scale":1,"position":{"pointX":360,"pointY":270},"width":720,"sublayerTransform":[1,0,0,0,0,1,0,0,0,0,1,0,0,0,0,1],"contentsRect":{"y":0,"x":0,"width":1,"height":1},"opacity":1,"edgeAntialiasingMask":251658240,"height":540,"hidden":false,"anchorPoint":{"pointX":0.5,"pointY":0.5}},"layers":[{"animations":[],"initialState":{"affineTransform":[1,0,0,1,0,0],"masksToBounds":false,"rotation":0,"scale":1,"position":{"pointX":360,"pointY":270},"width":720,"sublayerTransform":[1,0,0,0,0,1,0,0,0,0,1,0,0,0,0,1],"contentsRect":{"y":0,"x":0,"width":1,"height":1},"opacity":1,"edgeAntialiasingMask":251658240,"height":540,"hidden":false,"anchorPoint":{"pointX":0.5,"pointY":0.5}},"layers":[{"animations":[],"layers":[],"texturedRectangle":{"isBackgroundTexture":true,"singleTextureOpacity":1,"textureType":1,"textBaseline":0,"textXHeight":0,"isVerticalText":false},"initialState":{"affineTransform":[1,0,0,1,0,0],"masksToBounds":false,"rotation":0,"scale":1,"position":{"pointX":360,"pointY":270},"width":720,"sublayerTransform":[1,0,0,0,0,1,0,0,0,0,1,0,0,0,0,1],"contentsRect":{"y":0,"x":0,"width":1,"height":1},"opacity":1,"edgeAntialiasingMask":0,"height":540,"hidden":false,"anchorPoint":{"pointX":0.5,"pointY":0.5}},"texture":"061E52036B4D717608B06786659BDA42"}]}]},{"animations":[],"initialState":{"affineTransform":[1,0,0,1,0,0],"masksToBounds":false,"rotation":0,"scale":1,"position":{"pointX":360,"pointY":270},"width":720,"sublayerTransform":[1,0,0,0,0,1,0,0,0,0,1,0,0,0,0,1],"contentsRect":{"y":0,"x":0,"width":1,"height":1},"opacity":1,"edgeAntialiasingMask":251658240,"height":540,"hidden":false,"anchorPoint":{"pointX":0.5,"pointY":0.5}},"layers":[{"animations":[],"initialState":{"affineTransform":[1,0,0,1,0,0],"masksToBounds":false,"rotation":0,"scale":1,"position":{"pointX":280.75477600097656,"pointY":255.20000457763672},"width":311,"sublayerTransform":[1,0,0,0,0,1,0,0,0,0,1,0,0,0,0,1],"contentsRect":{"y":0,"x":0,"width":1,"height":1},"opacity":1,"edgeAntialiasingMask":251658240,"height":215,"hidden":false,"anchorPoint":{"pointX":0.5,"pointY":0.5}},"layers":[{"animations":[],"layers":[],"texturedRectangle":{"singleTextureOpacity":1,"textXHeight":0.16733284883720931,"textBaseline":1.0000145653934154,"isBackgroundTexture":true,"isVerticalText":false,"textColor":[0.70196080207824707,1,0.9960784912109375,1],"textureType":6},"initialState":{"affineTransform":[1,0,0,1,0,0],"masksToBounds":false,"rotation":0,"scale":1,"position":{"pointX":157.24522399902344,"pointY":125.79999542236328},"width":311,"sublayerTransform":[1,0,0,0,0,1,0,0,0,0,1,0,0,0,0,1],"contentsRect":{"y":0,"x":0,"width":1,"height":1},"opacity":1,"edgeAntialiasingMask":0,"height":215,"hidden":false,"anchorPoint":{"pointX":0.5,"pointY":0.5}},"texture":"4DE4776D86FE7C2E8679BF85BF26A28C"}]}]},{"animations":[],"initialState":{"affineTransform":[1,0,0,1,0,0],"masksToBounds":false,"rotation":0,"scale":1,"position":{"pointX":360,"pointY":270},"width":720,"sublayerTransform":[1,0,0,0,0,1,0,0,0,0,1,0,0,0,0,1],"contentsRect":{"y":0,"x":0,"width":1,"height":1},"opacity":1,"edgeAntialiasingMask":251658240,"height":540,"hidden":false,"anchorPoint":{"pointX":0.5,"pointY":0.5}},"layers":[{"animations":[],"initialState":{"affineTransform":[1,0,0,1,0,0],"masksToBounds":false,"rotation":0,"scale":1,"position":{"pointX":620,"pointY":58.5},"width":152,"sublayerTransform":[1,0,0,0,0,1,0,0,0,0,1,0,0,0,0,1],"contentsRect":{"y":0,"x":0,"width":1,"height":1},"opacity":1,"edgeAntialiasingMask":251658240,"height":77,"hidden":false,"anchorPoint":{"pointX":0.5,"pointY":0.5}},"layers":[{"animations":[],"layers":[],"texturedRectangle":{"isBackgroundTexture":true,"singleTextureOpacity":1,"textureType":5,"textBaseline":0,"textXHeight":0,"isVerticalText":false},"initialState":{"affineTransform":[1,0,0,1,0,0],"masksToBounds":false,"rotation":0,"scale":1,"position":{"pointX":75,"pointY":37.5},"width":152,"sublayerTransform":[1,0,0,0,0,1,0,0,0,0,1,0,0,0,0,1],"contentsRect":{"y":0,"x":0,"width":1,"height":1},"opacity":1,"edgeAntialiasingMask":0,"height":77,"hidden":false,"anchorPoint":{"pointX":0.5,"pointY":0.5}},"texture":"4CF0339B3675E8219B2D03F2AEDA6480"}]}]},{"animations":[],"initialState":{"affineTransform":[1,0,0,1,0,0],"masksToBounds":false,"rotation":0,"scale":1,"position":{"pointX":360,"pointY":270},"width":720,"sublayerTransform":[1,0,0,0,0,1,0,0,0,0,1,0,0,0,0,1],"contentsRect":{"y":0,"x":0,"width":1,"height":1},"opacity":1,"edgeAntialiasingMask":251658240,"height":540,"hidden":false,"anchorPoint":{"pointX":0.5,"pointY":0.5}},"layers":[{"animations":[],"initialState":{"affineTransform":[1,0,0,1,0,0],"masksToBounds":false,"rotation":0,"scale":1,"position":{"pointX":651.91827392578125,"pointY":469.11660766601562},"width":153,"sublayerTransform":[1,0,0,0,0,1,0,0,0,0,1,0,0,0,0,1],"contentsRect":{"y":0,"x":0,"width":1,"height":1},"opacity":1,"edgeAntialiasingMask":251658240,"height":144,"hidden":false,"anchorPoint":{"pointX":0.5,"pointY":0.5}},"layers":[{"animations":[],"layers":[],"texturedRectangle":{"isBackgroundTexture":true,"singleTextureOpacity":1,"textureType":5,"textBaseline":0,"textXHeight":0,"isVerticalText":false},"initialState":{"affineTransform":[1,0,0,1,0,0],"masksToBounds":false,"rotation":0,"scale":1,"position":{"pointX":75.08172607421875,"pointY":70.883392333984375},"width":153,"sublayerTransform":[1,0,0,0,0,1,0,0,0,0,1,0,0,0,0,1],"contentsRect":{"y":0,"x":0,"width":1,"height":1},"opacity":1,"edgeAntialiasingMask":0,"height":144,"hidden":false,"anchorPoint":{"pointX":0.5,"pointY":0.5}},"texture":"D88296A57128D65D7F60CFEBFF9D4F04"}]}]},{"animations":[],"initialState":{"affineTransform":[1,0,0,1,0,0],"masksToBounds":false,"rotation":0,"scale":1,"position":{"pointX":360,"pointY":270},"width":720,"sublayerTransform":[1,0,0,0,0,1,0,0,0,0,1,0,0,0,0,1],"contentsRect":{"y":0,"x":0,"width":1,"height":1},"opacity":1,"edgeAntialiasingMask":251658240,"height":540,"hidden":false,"anchorPoint":{"pointX":0.5,"pointY":0.5}},"layers":[{"animations":[],"initialState":{"affineTransform":[1,0,0,1,0,0],"masksToBounds":false,"rotation":0,"scale":1,"position":{"pointX":344.54765319824219,"pointY":300.96777153015137},"width":970,"sublayerTransform":[1,0,0,0,0,1,0,0,0,0,1,0,0,0,0,1],"contentsRect":{"y":0,"x":0,"width":1,"height":1},"opacity":1,"edgeAntialiasingMask":251658240,"height":643,"hidden":false,"anchorPoint":{"pointX":0.5,"pointY":0.5}},"objectID":"C773AFBD-4669-4E31-84E7-6E9044E3878D","layers":[{"animations":[],"layers":[],"texturedRectangle":{"isBackgroundTexture":true,"singleTextureOpacity":1,"textureType":5,"textBaseline":0,"textXHeight":0,"isVerticalText":false},"initialState":{"affineTransform":[1,0,0,1,0,0],"masksToBounds":false,"rotation":0,"scale":1,"position":{"pointX":483.45234680175781,"pointY":320.03222846984863},"width":970,"sublayerTransform":[1,0,0,0,0,1,0,0,0,0,1,0,0,0,0,1],"contentsRect":{"y":0,"x":0,"width":1,"height":1},"opacity":1,"edgeAntialiasingMask":0,"height":643,"hidden":true,"anchorPoint":{"pointX":0.5,"pointY":0.5}},"texture":"6C75AA76F78CD896B5939358DD4B7400"}]}]}]}},{"effects":[{"beginTime":0,"baseLayer":{"animations":[],"initialState":{"affineTransform":[1,0,0,1,0,0],"masksToBounds":false,"rotation":0,"scale":1,"position":{"pointX":360,"pointY":270},"width":720,"sublayerTransform":[1,0,0,0,0,1,0,0,0,0,1,0,0,0,0,1],"contentsRect":{"y":0,"x":0,"width":1,"height":1},"opacity":1,"edgeAntialiasingMask":251658240,"height":540,"hidden":false,"anchorPoint":{"pointX":0.5,"pointY":0.5}},"objectID":"0","layers":[{"animations":[],"initialState":{"affineTransform":[1,0,0,1,0,0],"masksToBounds":false,"rotation":0,"scale":1,"position":{"pointX":360,"pointY":270},"width":720,"sublayerTransform":[1,0,0,0,0,1,0,0,0,0,1,-0.00070015824933551967,0,0,0,1],"contentsRect":{"y":0,"x":0,"width":1,"height":1},"opacity":1,"edgeAntialiasingMask":251658240,"height":540,"hidden":false,"anchorPoint":{"pointX":0.5,"pointY":0.5}},"layers":[{"animations":[],"layers":[],"texturedRectangle":{"isBackgroundTexture":false,"singleTextureOpacity":1,"textureType":0,"textBaseline":0,"textXHeight":0,"isVerticalText":false},"initialState":{"affineTransform":[1,0,0,1,0,0],"masksToBounds":false,"rotation":0,"scale":1,"position":{"pointX":360,"pointY":270},"width":720,"sublayerTransform":[1,0,0,0,0,1,0,0,0,0,1,0,0,0,0,1],"contentsRect":{"y":0,"x":0,"width":1,"height":1},"opacity":1,"edgeAntialiasingMask":0,"height":540,"hidden":false,"anchorPoint":{"pointX":0.5,"pointY":0.5}},"texture":"20B48E0268FDEF10A2E2CC5243133BCA"},{"animations":[{"timeOffset":0,"from":{"scalar":false},"beginTime":0,"repeatCount":0,"fillMode":"both","property":"hidden","autoreverses":false,"duration":0.01,"to":{"scalar":true}}],"layers":[],"texturedRectangle":{"isBackgroundTexture":false,"singleTextureOpacity":1,"textureType":0,"textBaseline":0,"textXHeight":0,"isVerticalText":false},"initialState":{"affineTransform":[1,0,0,1,0,0],"masksToBounds":false,"rotation":0,"scale":1,"position":{"pointX":360,"pointY":270},"width":720,"sublayerTransform":[1,0,0,0,0,1,0,0,0,0,1,0,0,0,0,1],"contentsRect":{"y":0,"x":0,"width":1,"height":1},"opacity":1,"edgeAntialiasingMask":0,"height":540,"hidden":false,"anchorPoint":{"pointX":0.5,"pointY":0.5}},"texture":"EE4ED503C1F8A585FBFC66F1850A8D58"}]}]},"effects":[],"duration":0.01,"type":"transition","attributes":{"direction":0},"name":"none","objectID":"0"}],"automaticPlay":false,"hyperlinks":[],"accessibility":[{"text":"Pages from Logo_presentation.pdf","targetRectangle":{"y":397.11660766601562,"x":575.41827392578125,"width":150,"height":140.99588012695312}},{"text":"NSS 2017 LOGO_ENGLISH.png","targetRectangle":{"y":-20.532228469848633,"x":-140.45234680175781,"width":966.67742919921875,"height":639.78826904296875}},{"text":"rhulmasterlogocmyk.jpg","targetRectangle":{"y":20,"x":544,"width":150,"height":74.920677185058594}},{"text":"A quick word!","targetRectangle":{"y":150.70000457763672,"x":128.2547766852191,"width":307.81250917352736,"height":91}},{"text":" \\tHugh Shanahan ","targetRectangle":{"y":288.30000615119934,"x":128.2547766852191,"width":227.39063046667741,"height":60.000000655651093}},{"text":" \\tDirector of Student Experience","targetRectangle":{"y":348.30000680685043,"x":128.2547766852191,"width":293.66667410852403,"height":41}}],"baseLayer":{"animations":[],"initialState":{"affineTransform":[1,0,0,1,0,0],"masksToBounds":false,"rotation":0,"scale":1,"position":{"pointX":360,"pointY":270},"width":720,"sublayerTransform":[1,0,0,0,0,1,0,0,0,0,1,0,0,0,0,1],"contentsRect":{"y":0,"x":0,"width":1,"height":1},"opacity":1,"edgeAntialiasingMask":251658240,"height":540,"hidden":false,"anchorPoint":{"pointX":0.5,"pointY":0.5}},"objectID":"0","layers":[{"animations":[],"initialState":{"affineTransform":[1,0,0,1,0,0],"masksToBounds":false,"rotation":0,"scale":1,"position":{"pointX":360,"pointY":270},"width":720,"sublayerTransform":[1,0,0,0,0,1,0,0,0,0,1,-0.00070015824933551967,0,0,0,1],"contentsRect":{"y":0,"x":0,"width":1,"height":1},"opacity":1,"edgeAntialiasingMask":251658240,"height":540,"hidden":false,"anchorPoint":{"pointX":0.5,"pointY":0.5}},"layers":[{"animations":[],"layers":[],"texturedRectangle":{"isBackgroundTexture":false,"singleTextureOpacity":1,"textureType":0,"textBaseline":0,"textXHeight":0,"isVerticalText":false},"initialState":{"affineTransform":[1,0,0,1,0,0],"masksToBounds":false,"rotation":0,"scale":1,"position":{"pointX":360,"pointY":270},"width":720,"sublayerTransform":[1,0,0,0,0,1,0,0,0,0,1,0,0,0,0,1],"contentsRect":{"y":0,"x":0,"width":1,"height":1},"opacity":1,"edgeAntialiasingMask":0,"height":540,"hidden":false,"anchorPoint":{"pointX":0.5,"pointY":0.5}},"texture":"EE4ED503C1F8A585FBFC66F1850A8D58"}]}]}}]}